{
  "schema_version": "1.1",
  "date": "2026-02-23",
  "games": [
    {
      "id": "2026-02-23-mia-stl",
      "mlb_game_pk": 831485,
      "date": "2026-02-23",
      "game_time": "2026-02-23T18:05:00Z",
      "sport": "MLB",
      "status": "Final",
      "venue": {
        "id": 2520,
        "name": "Roger Dean Chevrolet Stadium"
      },
      "away_team": {
        "team_id": 146,
        "abbr": "MIA",
        "name": "Miami Marlins"
      },
      "home_team": {
        "team_id": 138,
        "abbr": "STL",
        "name": "St. Louis Cardinals"
      },
      "pitchers": {},
      "lineups": {},
      "pitcher_vs_lineup": {},
      "bullpens": {},
      "weather": {},
      "market": {},
      "controls": {
        "default_timeframe": "last_30",
        "default_location": "all"
      },
      "abstract_status": "Final",
      "score": {
        "away": 4,
        "home": 5
      },
      "linescore": {
        "scheduled_innings": 9,
        "current_inning": 9,
        "current_inning_ordinal": "9th",
        "innings": [
          {
            "num": 1,
            "ordinal": "1st",
            "away": 1,
            "home": 1
          },
          {
            "num": 2,
            "ordinal": "2nd",
            "away": 0,
            "home": 0
          },
          {
            "num": 3,
            "ordinal": "3rd",
            "away": 1,
            "home": 0
          },
          {
            "num": 4,
            "ordinal": "4th",
            "away": 0,
            "home": 1
          },
          {
            "num": 5,
            "ordinal": "5th",
            "away": 0,
            "home": 0
          },
          {
            "num": 6,
            "ordinal": "6th",
            "away": 1,
            "home": 0
          },
          {
            "num": 7,
            "ordinal": "7th",
            "away": 0,
            "home": 0
          },
          {
            "num": 8,
            "ordinal": "8th",
            "away": 1,
            "home": 0
          },
          {
            "num": 9,
            "ordinal": "9th",
            "away": 0,
            "home": 3
          }
        ],
        "totals": {
          "away": {
            "runs": 4,
            "hits": 9,
            "errors": 2
          },
          "home": {
            "runs": 5,
            "hits": 5,
            "errors": 1
          }
        }
      },
      "decisions": {
        "winner": {
          "id": 678016,
          "name": "Ian Bedell"
        },
        "loser": {
          "id": 814508,
          "name": "Colby Martin"
        }
      }
    },
    {
      "id": "2026-02-23-atl-bal",
      "mlb_game_pk": 831540,
      "date": "2026-02-23",
      "game_time": "2026-02-23T18:05:00Z",
      "sport": "MLB",
      "status": "Final",
      "venue": {
        "id": 2508,
        "name": "Ed Smith Stadium"
      },
      "away_team": {
        "team_id": 144,
        "abbr": "ATL",
        "name": "Atlanta Braves"
      },
      "home_team": {
        "team_id": 110,
        "abbr": "BAL",
        "name": "Baltimore Orioles"
      },
      "pitchers": {},
      "lineups": {},
      "pitcher_vs_lineup": {},
      "bullpens": {},
      "weather": {},
      "market": {},
      "controls": {
        "default_timeframe": "last_30",
        "default_location": "all"
      },
      "abstract_status": "Final",
      "score": {
        "away": 10,
        "home": 7
      },
      "linescore": {
        "scheduled_innings": 9,
        "current_inning": 9,
        "current_inning_ordinal": "9th",
        "innings": [
          {
            "num": 1,
            "ordinal": "1st",
            "away": 0,
            "home": 0
          },
          {
            "num": 2,
            "ordinal": "2nd",
            "away": 0,
            "home": 0
          },
          {
            "num": 3,
            "ordinal": "3rd",
            "away": 2,
            "home": 0
          },
          {
            "num": 4,
            "ordinal": "4th",
            "away": 0,
            "home": 0
          },
          {
            "num": 5,
            "ordinal": "5th",
            "away": 0,
            "home": 3
          },
          {
            "num": 6,
            "ordinal": "6th",
            "away": 8,
            "home": 1
          },
          {
            "num": 7,
            "ordinal": "7th",
            "away": 0,
            "home": 1
          },
          {
            "num": 8,
            "ordinal": "8th",
            "away": 0,
            "home": 2
          },
          {
            "num": 9,
            "ordinal": "9th",
            "away": 0,
            "home": 0
          }
        ],
        "totals": {
          "away": {
            "runs": 10,
            "hits": 13,
            "errors": 1
          },
          "home": {
            "runs": 7,
            "hits": 9,
            "errors": 1
          }
        }
      },
      "decisions": {
        "winner": {
          "id": 693176,
          "name": "Elison Joseph"
        },
        "loser": {
          "id": 660600,
          "name": "Enoli Paredes"
        },
        "save": {
          "id": 686608,
          "name": "Jacob Wallace"
        }
      }
    },
    {
      "id": "2026-02-23-nyy-pit",
      "mlb_game_pk": 831595,
      "date": "2026-02-23",
      "game_time": "2026-02-23T18:05:00Z",
      "sport": "MLB",
      "status": "Final",
      "venue": {
        "id": 2526,
        "name": "LECOM Park"
      },
      "away_team": {
        "team_id": 147,
        "abbr": "NYY",
        "name": "New York Yankees"
      },
      "home_team": {
        "team_id": 134,
        "abbr": "PIT",
        "name": "Pittsburgh Pirates"
      },
      "pitchers": {},
      "lineups": {},
      "pitcher_vs_lineup": {},
      "bullpens": {},
      "weather": {},
      "market": {},
      "controls": {
        "default_timeframe": "last_30",
        "default_location": "all"
      },
      "abstract_status": "Final",
      "score": {
        "away": 6,
        "home": 2
      },
      "linescore": {
        "scheduled_innings": 9,
        "current_inning": 9,
        "current_inning_ordinal": "9th",
        "innings": [
          {
            "num": 1,
            "ordinal": "1st",
            "away": 0,
            "home": 1
          },
          {
            "num": 2,
            "ordinal": "2nd",
            "away": 4,
            "home": 0
          },
          {
            "num": 3,
            "ordinal": "3rd",
            "away": 0,
            "home": 0
          },
          {
            "num": 4,
            "ordinal": "4th",
            "away": 0,
            "home": 0
          },
          {
            "num": 5,
            "ordinal": "5th",
            "away": 0,
            "home": 0
          },
          {
            "num": 6,
            "ordinal": "6th",
            "away": 0,
            "home": 0
          },
          {
            "num": 7,
            "ordinal": "7th",
            "away": 1,
            "home": 0
          },
          {
            "num": 8,
            "ordinal": "8th",
            "away": 1,
            "home": 1
          },
          {
            "num": 9,
            "ordinal": "9th",
            "away": 0,
            "home": 0
          }
        ],
        "totals": {
          "away": {
            "runs": 6,
            "hits": 5,
            "errors": 0
          },
          "home": {
            "runs": 2,
            "hits": 10,
            "errors": 1
          }
        }
      },
      "decisions": {
        "winner": {
          "id": 642232,
          "name": "Ryan Yarbrough"
        },
        "loser": {
          "id": 696149,
          "name": "Bubba Chandler"
        }
      }
    },
    {
      "id": "2026-02-23-bos-tb",
      "mlb_game_pk": 831652,
      "date": "2026-02-23",
      "game_time": "2026-02-23T18:05:00Z",
      "sport": "MLB",
      "status": "Final",
      "venue": {
        "id": 2534,
        "name": "Charlotte Sports Park"
      },
      "away_team": {
        "team_id": 111,
        "abbr": "BOS",
        "name": "Boston Red Sox"
      },
      "home_team": {
        "team_id": 139,
        "abbr": "TB",
        "name": "Tampa Bay Rays"
      },
      "pitchers": {},
      "lineups": {},
      "pitcher_vs_lineup": {},
      "bullpens": {},
      "weather": {},
      "market": {},
      "controls": {
        "default_timeframe": "last_30",
        "default_location": "all"
      },
      "abstract_status": "Final",
      "score": {
        "away": 1,
        "home": 2
      },
      "linescore": {
        "scheduled_innings": 9,
        "current_inning": 9,
        "current_inning_ordinal": "9th",
        "innings": [
          {
            "num": 1,
            "ordinal": "1st",
            "away": 0,
            "home": 0
          },
          {
            "num": 2,
            "ordinal": "2nd",
            "away": 0,
            "home": 0
          },
          {
            "num": 3,
            "ordinal": "3rd",
            "away": 0,
            "home": 0
          },
          {
            "num": 4,
            "ordinal": "4th",
            "away": 0,
            "home": 0
          },
          {
            "num": 5,
            "ordinal": "5th",
            "away": 0,
            "home": 0
          },
          {
            "num": 6,
            "ordinal": "6th",
            "away": 0,
            "home": 0
          },
          {
            "num": 7,
            "ordinal": "7th",
            "away": 0,
            "home": 0
          },
          {
            "num": 8,
            "ordinal": "8th",
            "away": 0,
            "home": 0
          },
          {
            "num": 9,
            "ordinal": "9th",
            "away": 1,
            "home": 2
          }
        ],
        "totals": {
          "away": {
            "runs": 1,
            "hits": 8,
            "errors": 0
          },
          "home": {
            "runs": 2,
            "hits": 5,
            "errors": 0
          }
        }
      },
      "decisions": {
        "winner": {
          "id": 694680,
          "name": "Trevor Martin"
        },
        "loser": {
          "id": 814810,
          "name": "Calvin Bickerstaff"
        }
      }
    },
    {
      "id": "2026-02-23-min-det",
      "mlb_game_pk": 831658,
      "date": "2026-02-23",
      "game_time": "2026-02-23T18:05:00Z",
      "sport": "MLB",
      "status": "Final",
      "venue": {
        "id": 2511,
        "name": "Publix Field at Joker Marchant Stadium"
      },
      "away_team": {
        "team_id": 142,
        "abbr": "MIN",
        "name": "Minnesota Twins"
      },
      "home_team": {
        "team_id": 116,
        "abbr": "DET",
        "name": "Detroit Tigers"
      },
      "pitchers": {},
      "lineups": {},
      "pitcher_vs_lineup": {},
      "bullpens": {},
      "weather": {},
      "market": {},
      "controls": {
        "default_timeframe": "last_30",
        "default_location": "all"
      },
      "abstract_status": "Final",
      "score": {
        "away": 3,
        "home": 0
      },
      "linescore": {
        "scheduled_innings": 9,
        "current_inning": 9,
        "current_inning_ordinal": "9th",
        "innings": [
          {
            "num": 1,
            "ordinal": "1st",
            "away": 0,
            "home": 0
          },
          {
            "num": 2,
            "ordinal": "2nd",
            "away": 0,
            "home": 0
          },
          {
            "num": 3,
            "ordinal": "3rd",
            "away": 0,
            "home": 0
          },
          {
            "num": 4,
            "ordinal": "4th",
            "away": 0,
            "home": 0
          },
          {
            "num": 5,
            "ordinal": "5th",
            "away": 1,
            "home": 0
          },
          {
            "num": 6,
            "ordinal": "6th",
            "away": 0,
            "home": 0
          },
          {
            "num": 7,
            "ordinal": "7th",
            "away": 1,
            "home": 0
          },
          {
            "num": 8,
            "ordinal": "8th",
            "away": 1,
            "home": 0
          },
          {
            "num": 9,
            "ordinal": "9th",
            "away": 0,
            "home": 0
          }
        ],
        "totals": {
          "away": {
            "runs": 3,
            "hits": 7,
            "errors": 2
          },
          "home": {
            "runs": 0,
            "hits": 3,
            "errors": 0
          }
        }
      },
      "decisions": {
        "winner": {
          "id": 687570,
          "name": "Connor Prielipp"
        },
        "loser": {
          "id": 676428,
          "name": "Brant Hurter"
        },
        "save": {
          "id": 687879,
          "name": "Luis Quiñones"
        }
      }
    },
    {
      "id": "2026-02-23-nym-tor",
      "mlb_game_pk": 831539,
      "date": "2026-02-23",
      "game_time": "2026-02-23T18:07:00Z",
      "sport": "MLB",
      "status": "Final",
      "venue": {
        "id": 2536,
        "name": "TD Ballpark"
      },
      "away_team": {
        "team_id": 121,
        "abbr": "NYM",
        "name": "New York Mets"
      },
      "home_team": {
        "team_id": 141,
        "abbr": "TOR",
        "name": "Toronto Blue Jays"
      },
      "pitchers": {},
      "lineups": {},
      "pitcher_vs_lineup": {},
      "bullpens": {},
      "weather": {},
      "market": {},
      "controls": {
        "default_timeframe": "last_30",
        "default_location": "all"
      },
      "abstract_status": "Final",
      "score": {
        "away": 4,
        "home": 3
      },
      "linescore": {
        "scheduled_innings": 9,
        "current_inning": 9,
        "current_inning_ordinal": "9th",
        "innings": [
          {
            "num": 1,
            "ordinal": "1st",
            "away": 0,
            "home": 0
          },
          {
            "num": 2,
            "ordinal": "2nd",
            "away": 0,
            "home": 2
          },
          {
            "num": 3,
            "ordinal": "3rd",
            "away": 2,
            "home": 0
          },
          {
            "num": 4,
            "ordinal": "4th",
            "away": 0,
            "home": 0
          },
          {
            "num": 5,
            "ordinal": "5th",
            "away": 0,
            "home": 0
          },
          {
            "num": 6,
            "ordinal": "6th",
            "away": 1,
            "home": 0
          },
          {
            "num": 7,
            "ordinal": "7th",
            "away": 1,
            "home": 0
          },
          {
            "num": 8,
            "ordinal": "8th",
            "away": 0,
            "home": 0
          },
          {
            "num": 9,
            "ordinal": "9th",
            "away": 0,
            "home": 1
          }
        ],
        "totals": {
          "away": {
            "runs": 4,
            "hits": 6,
            "errors": 0
          },
          "home": {
            "runs": 3,
            "hits": 7,
            "errors": 2
          }
        }
      },
      "decisions": {
        "winner": {
          "id": 668964,
          "name": "Tobias Myers"
        },
        "loser": {
          "id": 660896,
          "name": "Jorge Alcala"
        },
        "save": {
          "id": 690736,
          "name": "Trey McGough"
        }
      }
    },
    {
      "id": "2026-02-23-sea-lad",
      "mlb_game_pk": 831745,
      "date": "2026-02-23",
      "game_time": "2026-02-23T20:05:00Z",
      "sport": "MLB",
      "status": "Final",
      "venue": {
        "id": 3809,
        "name": "Camelback Ranch"
      },
      "away_team": {
        "team_id": 136,
        "abbr": "SEA",
        "name": "Seattle Mariners"
      },
      "home_team": {
        "team_id": 119,
        "abbr": "LAD",
        "name": "Los Angeles Dodgers"
      },
      "pitchers": {},
      "lineups": {},
      "pitcher_vs_lineup": {},
      "bullpens": {},
      "weather": {},
      "market": {},
      "controls": {
        "default_timeframe": "last_30",
        "default_location": "all"
      },
      "abstract_status": "Final",
      "score": {
        "away": 0,
        "home": 3
      },
      "linescore": {
        "scheduled_innings": 9,
        "current_inning": 9,
        "current_inning_ordinal": "9th",
        "innings": [
          {
            "num": 1,
            "ordinal": "1st",
            "away": 0,
            "home": 0
          },
          {
            "num": 2,
            "ordinal": "2nd",
            "away": 0,
            "home": 0
          },
          {
            "num": 3,
            "ordinal": "3rd",
            "away": 0,
            "home": 0
          },
          {
            "num": 4,
            "ordinal": "4th",
            "away": 0,
            "home": 2
          },
          {
            "num": 5,
            "ordinal": "5th",
            "away": 0,
            "home": 0
          },
          {
            "num": 6,
            "ordinal": "6th",
            "away": 0,
            "home": 1
          },
          {
            "num": 7,
            "ordinal": "7th",
            "away": 0,
            "home": 0
          },
          {
            "num": 8,
            "ordinal": "8th",
            "away": 0,
            "home": 0
          },
          {
            "num": 9,
            "ordinal": "9th",
            "away": 0,
            "home": null
          }
        ],
        "totals": {
          "away": {
            "runs": 0,
            "hits": 4,
            "errors": 1
          },
          "home": {
            "runs": 3,
            "hits": 10,
            "errors": 0
          }
        }
      },
      "decisions": {
        "winner": {
          "id": 669165,
          "name": "Kyle Hurt"
        },
        "loser": {
          "id": 678606,
          "name": "José A. Ferrer"
        },
        "save": {
          "id": 687798,
          "name": "Nick Robertson"
        }
      }
    },
    {
      "id": "2026-02-23-chc-kc",
      "mlb_game_pk": 831927,
      "date": "2026-02-23",
      "game_time": "2026-02-23T20:05:00Z",
      "sport": "MLB",
      "status": "Final",
      "venue": {
        "id": 2603,
        "name": "Surprise Stadium"
      },
      "away_team": {
        "team_id": 112,
        "abbr": "CHC",
        "name": "Chicago Cubs"
      },
      "home_team": {
        "team_id": 118,
        "abbr": "KC",
        "name": "Kansas City Royals"
      },
      "pitchers": {},
      "lineups": {},
      "pitcher_vs_lineup": {},
      "bullpens": {},
      "weather": {},
      "market": {},
      "controls": {
        "default_timeframe": "last_30",
        "default_location": "all"
      },
      "abstract_status": "Final",
      "score": {
        "away": 3,
        "home": 2
      },
      "linescore": {
        "scheduled_innings": 9,
        "current_inning": 9,
        "current_inning_ordinal": "9th",
        "innings": [
          {
            "num": 1,
            "ordinal": "1st",
            "away": 0,
            "home": 0
          },
          {
            "num": 2,
            "ordinal": "2nd",
            "away": 0,
            "home": 0
          },
          {
            "num": 3,
            "ordinal": "3rd",
            "away": 0,
            "home": 0
          },
          {
            "num": 4,
            "ordinal": "4th",
            "away": 1,
            "home": 0
          },
          {
            "num": 5,
            "ordinal": "5th",
            "away": 2,
            "home": 0
          },
          {
            "num": 6,
            "ordinal": "6th",
            "away": 0,
            "home": 0
          },
          {
            "num": 7,
            "ordinal": "7th",
            "away": 0,
            "home": 0
          },
          {
            "num": 8,
            "ordinal": "8th",
            "away": 0,
            "home": 1
          },
          {
            "num": 9,
            "ordinal": "9th",
            "away": 0,
            "home": 1
          }
        ],
        "totals": {
          "away": {
            "runs": 3,
            "hits": 6,
            "errors": 0
          },
          "home": {
            "runs": 2,
            "hits": 7,
            "errors": 1
          }
        }
      },
      "decisions": {
        "winner": {
          "id": 665871,
          "name": "Javier Assad"
        },
        "loser": {
          "id": 679883,
          "name": "Luinder Avila"
        },
        "save": {
          "id": 689608,
          "name": "Walker Powell"
        }
      }
    },
    {
      "id": "2026-02-23-ath-sf",
      "mlb_game_pk": 831939,
      "date": "2026-02-23",
      "game_time": "2026-02-23T20:05:00Z",
      "sport": "MLB",
      "status": "Final",
      "venue": {
        "id": 2532,
        "name": "Scottsdale Stadium"
      },
      "away_team": {
        "team_id": 133,
        "abbr": "ATH",
        "name": "Athletics"
      },
      "home_team": {
        "team_id": 137,
        "abbr": "SF",
        "name": "San Francisco Giants"
      },
      "pitchers": {},
      "lineups": {},
      "pitcher_vs_lineup": {},
      "bullpens": {},
      "weather": {},
      "market": {},
      "controls": {
        "default_timeframe": "last_30",
        "default_location": "all"
      },
      "abstract_status": "Final",
      "score": {
        "away": 2,
        "home": 6
      },
      "linescore": {
        "scheduled_innings": 9,
        "current_inning": 9,
        "current_inning_ordinal": "9th",
        "innings": [
          {
            "num": 1,
            "ordinal": "1st",
            "away": 2,
            "home": 0
          },
          {
            "num": 2,
            "ordinal": "2nd",
            "away": 0,
            "home": 0
          },
          {
            "num": 3,
            "ordinal": "3rd",
            "away": 0,
            "home": 1
          },
          {
            "num": 4,
            "ordinal": "4th",
            "away": 0,
            "home": 1
          },
          {
            "num": 5,
            "ordinal": "5th",
            "away": 0,
            "home": 1
          },
          {
            "num": 6,
            "ordinal": "6th",
            "away": 0,
            "home": 1
          },
          {
            "num": 7,
            "ordinal": "7th",
            "away": 0,
            "home": 1
          },
          {
            "num": 8,
            "ordinal": "8th",
            "away": 0,
            "home": 1
          },
          {
            "num": 9,
            "ordinal": "9th",
            "away": 0,
            "home": null
          }
        ],
        "totals": {
          "away": {
            "runs": 2,
            "hits": 10,
            "errors": 2
          },
          "home": {
            "runs": 6,
            "hits": 11,
            "errors": 1
          }
        }
      },
      "decisions": {
        "winner": {
          "id": 805661,
          "name": "Greg Farone"
        },
        "loser": {
          "id": 665660,
          "name": "Elvis Alvarado"
        }
      }
    },
    {
      "id": "2026-02-23-az-cle",
      "mlb_game_pk": 831955,
      "date": "2026-02-23",
      "game_time": "2026-02-23T20:05:00Z",
      "sport": "MLB",
      "status": "Final",
      "venue": {
        "id": 3834,
        "name": "Goodyear Ballpark"
      },
      "away_team": {
        "team_id": 109,
        "abbr": "AZ",
        "name": "Arizona Diamondbacks"
      },
      "home_team": {
        "team_id": 114,
        "abbr": "CLE",
        "name": "Cleveland Guardians"
      },
      "pitchers": {},
      "lineups": {},
      "pitcher_vs_lineup": {},
      "bullpens": {},
      "weather": {},
      "market": {},
      "controls": {
        "default_timeframe": "last_30",
        "default_location": "all"
      },
      "abstract_status": "Final",
      "score": {
        "away": 5,
        "home": 9
      },
      "linescore": {
        "scheduled_innings": 9,
        "current_inning": 9,
        "current_inning_ordinal": "9th",
        "innings": [
          {
            "num": 1,
            "ordinal": "1st",
            "away": 0,
            "home": 0
          },
          {
            "num": 2,
            "ordinal": "2nd",
            "away": 0,
            "home": 0
          },
          {
            "num": 3,
            "ordinal": "3rd",
            "away": 0,
            "home": 2
          },
          {
            "num": 4,
            "ordinal": "4th",
            "away": 0,
            "home": 0
          },
          {
            "num": 5,
            "ordinal": "5th",
            "away": 0,
            "home": 3
          },
          {
            "num": 6,
            "ordinal": "6th",
            "away": 0,
            "home": 2
          },
          {
            "num": 7,
            "ordinal": "7th",
            "away": 3,
            "home": 0
          },
          {
            "num": 8,
            "ordinal": "8th",
            "away": 2,
            "home": 2
          },
          {
            "num": 9,
            "ordinal": "9th",
            "away": 0,
            "home": null
          }
        ],
        "totals": {
          "away": {
            "runs": 5,
            "hits": 11,
            "errors": 0
          },
          "home": {
            "runs": 9,
            "hits": 11,
            "errors": 0
          }
        }
      },
      "decisions": {
        "winner": {
          "id": 670036,
          "name": "Matt Festa"
        },
        "loser": {
          "id": 686228,
          "name": "Juan Burgos"
        }
      }
    },
    {
      "id": "2026-02-23-tex-laa",
      "mlb_game_pk": 831724,
      "date": "2026-02-23",
      "game_time": "2026-02-23T20:10:00Z",
      "sport": "MLB",
      "status": "Final",
      "venue": {
        "id": 2500,
        "name": "Tempe Diablo Stadium"
      },
      "away_team": {
        "team_id": 140,
        "abbr": "TEX",
        "name": "Texas Rangers"
      },
      "home_team": {
        "team_id": 108,
        "abbr": "LAA",
        "name": "Los Angeles Angels"
      },
      "pitchers": {},
      "lineups": {},
      "pitcher_vs_lineup": {},
      "bullpens": {},
      "weather": {},
      "market": {},
      "controls": {
        "default_timeframe": "last_30",
        "default_location": "all"
      },
      "abstract_status": "Final",
      "score": {
        "away": 6,
        "home": 0
      },
      "linescore": {
        "scheduled_innings": 9,
        "current_inning": 9,
        "current_inning_ordinal": "9th",
        "innings": [
          {
            "num": 1,
            "ordinal": "1st",
            "away": 3,
            "home": 0
          },
          {
            "num": 2,
            "ordinal": "2nd",
            "away": 0,
            "home": 0
          },
          {
            "num": 3,
            "ordinal": "3rd",
            "away": 0,
            "home": 0
          },
          {
            "num": 4,
            "ordinal": "4th",
            "away": 3,
            "home": 0
          },
          {
            "num": 5,
            "ordinal": "5th",
            "away": 0,
            "home": 0
          },
          {
            "num": 6,
            "ordinal": "6th",
            "away": 0,
            "home": 0
          },
          {
            "num": 7,
            "ordinal": "7th",
            "away": 0,
            "home": 0
          },
          {
            "num": 8,
            "ordinal": "8th",
            "away": 0,
            "home": 0
          },
          {
            "num": 9,
            "ordinal": "9th",
            "away": 0,
            "home": 0
          }
        ],
        "totals": {
          "away": {
            "runs": 6,
            "hits": 7,
            "errors": 0
          },
          "home": {
            "runs": 0,
            "hits": 8,
            "errors": 0
          }
        }
      },
      "decisions": {
        "winner": {
          "id": 683004,
          "name": "Jack Leiter"
        },
        "loser": {
          "id": 672282,
          "name": "Reid Detmers"
        }
      }
    },
    {
      "id": "2026-02-23-mil-sd",
      "mlb_game_pk": 831783,
      "date": "2026-02-23",
      "game_time": "2026-02-23T20:10:00Z",
      "sport": "MLB",
      "status": "Final",
      "venue": {
        "id": 2530,
        "name": "Peoria Stadium"
      },
      "away_team": {
        "team_id": 158,
        "abbr": "MIL",
        "name": "Milwaukee Brewers"
      },
      "home_team": {
        "team_id": 135,
        "abbr": "SD",
        "name": "San Diego Padres"
      },
      "pitchers": {},
      "lineups": {},
      "pitcher_vs_lineup": {},
      "bullpens": {},
      "weather": {},
      "market": {},
      "controls": {
        "default_timeframe": "last_30",
        "default_location": "all"
      },
      "abstract_status": "Final",
      "score": {
        "away": 5,
        "home": 7
      },
      "linescore": {
        "scheduled_innings": 9,
        "current_inning": 9,
        "current_inning_ordinal": "9th",
        "innings": [
          {
            "num": 1,
            "ordinal": "1st",
            "away": 4,
            "home": 0
          },
          {
            "num": 2,
            "ordinal": "2nd",
            "away": 0,
            "home": 0
          },
          {
            "num": 3,
            "ordinal": "3rd",
            "away": 0,
            "home": 0
          },
          {
            "num": 4,
            "ordinal": "4th",
            "away": 0,
            "home": 1
          },
          {
            "num": 5,
            "ordinal": "5th",
            "away": 0,
            "home": 0
          },
          {
            "num": 6,
            "ordinal": "6th",
            "away": 0,
            "home": 0
          },
          {
            "num": 7,
            "ordinal": "7th",
            "away": 1,
            "home": 0
          },
          {
            "num": 8,
            "ordinal": "8th",
            "away": 0,
            "home": 6
          },
          {
            "num": 9,
            "ordinal": "9th",
            "away": 0,
            "home": null
          }
        ],
        "totals": {
          "away": {
            "runs": 5,
            "hits": 9,
            "errors": 0
          },
          "home": {
            "runs": 7,
            "hits": 9,
            "errors": 0
          }
        }
      },
      "decisions": {
        "winner": {
          "id": 701195,
          "name": "Manuel Castro"
        },
        "loser": {
          "id": 807723,
          "name": "Bjorn Johnson"
        },
        "save": {
          "id": 678184,
          "name": "Garrett Hawkins"
        }
      }
    },
    {
      "id": "2026-02-23-cws-col",
      "mlb_game_pk": 831912,
      "date": "2026-02-23",
      "game_time": "2026-02-23T20:10:00Z",
      "sport": "MLB",
      "status": "Final",
      "venue": {
        "id": 4249,
        "name": "Salt River Fields at Talking Stick"
      },
      "away_team": {
        "team_id": 145,
        "abbr": "CWS",
        "name": "Chicago White Sox"
      },
      "home_team": {
        "team_id": 115,
        "abbr": "COL",
        "name": "Colorado Rockies"
      },
      "pitchers": {},
      "lineups": {},
      "pitcher_vs_lineup": {},
      "bullpens": {},
      "weather": {},
      "market": {},
      "controls": {
        "default_timeframe": "last_30",
        "default_location": "all"
      },
      "abstract_status": "Final",
      "score": {
        "away": 4,
        "home": 5
      },
      "linescore": {
        "scheduled_innings": 9,
        "current_inning": 9,
        "current_inning_ordinal": "9th",
        "innings": [
          {
            "num": 1,
            "ordinal": "1st",
            "away": 0,
            "home": 3
          },
          {
            "num": 2,
            "ordinal": "2nd",
            "away": 1,
            "home": 0
          },
          {
            "num": 3,
            "ordinal": "3rd",
            "away": 0,
            "home": 0
          },
          {
            "num": 4,
            "ordinal": "4th",
            "away": 0,
            "home": 0
          },
          {
            "num": 5,
            "ordinal": "5th",
            "away": 0,
            "home": 0
          },
          {
            "num": 6,
            "ordinal": "6th",
            "away": 0,
            "home": 0
          },
          {
            "num": 7,
            "ordinal": "7th",
            "away": 1,
            "home": 1
          },
          {
            "num": 8,
            "ordinal": "8th",
            "away": 2,
            "home": 0
          },
          {
            "num": 9,
            "ordinal": "9th",
            "away": 0,
            "home": 1
          }
        ],
        "totals": {
          "away": {
            "runs": 4,
            "hits": 11,
            "errors": 1
          },
          "home": {
            "runs": 5,
            "hits": 6,
            "errors": 0
          }
        }
      },
      "decisions": {
        "winner": {
          "id": 669445,
          "name": "Adam Laskey"
        },
        "loser": {
          "id": 690294,
          "name": "Shane Murphy"
        }
      }
    },
    {
      "id": "2026-02-23-phi-wsh",
      "mlb_game_pk": 831483,
      "date": "2026-02-23",
      "game_time": "2026-02-23T23:05:00Z",
      "sport": "MLB",
      "status": "Final",
      "venue": {
        "id": 5000,
        "name": "CACTI Park of the Palm Beaches"
      },
      "away_team": {
        "team_id": 143,
        "abbr": "PHI",
        "name": "Philadelphia Phillies"
      },
      "home_team": {
        "team_id": 120,
        "abbr": "WSH",
        "name": "Washington Nationals"
      },
      "pitchers": {},
      "lineups": {},
      "pitcher_vs_lineup": {},
      "bullpens": {},
      "weather": {},
      "market": {},
      "controls": {
        "default_timeframe": "last_30",
        "default_location": "all"
      },
      "abstract_status": "Final",
      "score": {
        "away": 5,
        "home": 5
      },
      "linescore": {
        "scheduled_innings": 9,
        "current_inning": 9,
        "current_inning_ordinal": "9th",
        "innings": [
          {
            "num": 1,
            "ordinal": "1st",
            "away": 0,
            "home": 1
          },
          {
            "num": 2,
            "ordinal": "2nd",
            "away": 0,
            "home": 0
          },
          {
            "num": 3,
            "ordinal": "3rd",
            "away": 1,
            "home": 0
          },
          {
            "num": 4,
            "ordinal": "4th",
            "away": 0,
            "home": 0
          },
          {
            "num": 5,
            "ordinal": "5th",
            "away": 0,
            "home": 0
          },
          {
            "num": 6,
            "ordinal": "6th",
            "away": 4,
            "home": 0
          },
          {
            "num": 7,
            "ordinal": "7th",
            "away": 0,
            "home": 2
          },
          {
            "num": 8,
            "ordinal": "8th",
            "away": 0,
            "home": 2
          },
          {
            "num": 9,
            "ordinal": "9th",
            "away": 0,
            "home": 0
          }
        ],
        "totals": {
          "away": {
            "runs": 5,
            "hits": 6,
            "errors": 0
          },
          "home": {
            "runs": 5,
            "hits": 6,
            "errors": 4
          }
        }
      },
      "decisions": {}
    }
  ],
  "updated_at": "2026-07-19T12:21:40.109308Z",
  "result_sync": {
    "source": "MLB Stats API schedule",
    "synced_at": "2026-07-19T12:21:40.109312Z",
    "official_game_count": 14
  }
}
